napari_graph/__init__.py
napari_graph/_version.py
napari_graph/base_graph.py
napari_graph/directed_graph.py
napari_graph/interops.py
napari_graph/numba.py
napari_graph/undirected_graph.py
napari_graph/_tests/test_graph.py
napari_graph/_tests/test_interops.py
napari_graph-0.2.2.dist-info/LICENSE
napari_graph-0.2.2.dist-info/METADATA
napari_graph-0.2.2.dist-info/WHEEL
napari_graph-0.2.2.dist-info/top_level.txt
napari_graph-0.2.2.dist-info/RECORD
